anonymiser/__init__.py
anonymiser/apps.py
anonymiser/db/__init__.py
anonymiser/db/functions.py
anonymiser/decorators.py
anonymiser/management/__init__.py
anonymiser/management/commands/__init__.py
anonymiser/management/commands/anonymisation_config.py
anonymiser/models.py
anonymiser/redacters.py
anonymiser/registry.py
anonymiser/settings.py
anonymiser/templates/anonymiser/anonymisation_config.csv
anonymiser/templates/anonymiser/anonymisation_config.md
django_anonymise-0.5.0.dist-info/METADATA
django_anonymise-0.5.0.dist-info/WHEEL
django_anonymise-0.5.0.dist-info/licenses/LICENSE
django_anonymise-0.5.0.dist-info/RECORD
